jupyter_remote_kernel-2.7.1.dist-info/licenses/LICENSE
remote_kernel/__init__.py
remote_kernel/core.py
jupyter_remote_kernel-2.7.1.dist-info/METADATA
jupyter_remote_kernel-2.7.1.dist-info/WHEEL
jupyter_remote_kernel-2.7.1.dist-info/entry_points.txt
jupyter_remote_kernel-2.7.1.dist-info/top_level.txt
jupyter_remote_kernel-2.7.1.dist-info/RECORD
