Metadata-Version: 2.4
Name: jupyter_remote_kernel
Version: 2.7.1
Summary: Remote Jupyter Kernel Launcher with SSH port forwarding
Author-email: Leo <leoustc@icloud.com>
Requires-Python: >=3.8
License-File: LICENSE
Requires-Dist: paramiko>=3.4.0
Requires-Dist: sshtunnel>=0.4.0
Requires-Dist: pydantic
Dynamic: license-file
